graph_searcher/__init__.py
graph_searcher/data_structures/__init__.py
graph_searcher/data_structures/edge/__init__.py
graph_searcher/data_structures/edge/edge.py
graph_searcher/data_structures/graph/__init__.py
graph_searcher/data_structures/graph/graph.py
graph_searcher/data_structures/vertex/__init__.py
graph_searcher/data_structures/vertex/vertex.py
graph_searcher/ui/__init__.py
graph_searcher/ui/cli/__init__.py
graph_searcher/ui/cli/cli.py
graph_searcher/ui/cli/json_file_action.py
graph_searcher-0.1.0.dist-info/entry_points.txt
graph_searcher-0.1.0.dist-info/WHEEL
graph_searcher-0.1.0.dist-info/METADATA
graph_searcher-0.1.0.dist-info/RECORD
