Metadata-Version: 2.1
Name: graph-searcher
Version: 0.1.0
Summary: A visual representation of search algorithms for graphs
Author: Pablo
Author-email: pablohuggem@gmail.com
Requires-Python: >=3.10,<4.0
Classifier: Programming Language :: Python :: 3
Classifier: Programming Language :: Python :: 3.10
Classifier: Programming Language :: Python :: 3.11
Requires-Dist: celluloid
Requires-Dist: matplotlib
Requires-Dist: numpy
Requires-Dist: spatialmath-python
